ayx_blackbird/__init__.py
ayx_blackbird/__main__.py
ayx_blackbird/version.py
ayx_blackbird/anchors/__init__.py
ayx_blackbird/anchors/input_anchor.py
ayx_blackbird/anchors/output_anchor.py
ayx_blackbird/assets/base_tool_config/Config.xml
ayx_blackbird/assets/base_tool_config/icon.png
ayx_blackbird/config/__init__.py
ayx_blackbird/config/tool_config.py
ayx_blackbird/config/workflow_config.py
ayx_blackbird/core/__init__.py
ayx_blackbird/core/base_plugin.py
ayx_blackbird/core/connection_callback_strategy.py
ayx_blackbird/core/connection_interface.py
ayx_blackbird/core/events.py
ayx_blackbird/mixins/__init__.py
ayx_blackbird/mixins/anchor_utils_mixin.py
ayx_blackbird/mixins/observable_mixin.py
ayx_blackbird/proxies/__init__.py
ayx_blackbird/proxies/engine_proxy.py
ayx_blackbird/proxies/field_proxy.py
ayx_blackbird/proxies/record_copier_proxy.py
ayx_blackbird/records/__init__.py
ayx_blackbird/records/base_record_container.py
ayx_blackbird/records/parsed_record_container.py
ayx_blackbird/records/raw_record_container.py
ayx_blackbird/records/utilities.py
ayx_blackbird/utilities/__init__.py
ayx_blackbird/utilities/constants.py
ayx_blackbird/utilities/exceptions.py
ayx_blackbird/utilities/validators.py
ayx_blackbird-1.0.0a2.dist-info/LICENSE
ayx_blackbird-1.0.0a2.dist-info/METADATA
ayx_blackbird-1.0.0a2.dist-info/WHEEL
ayx_blackbird-1.0.0a2.dist-info/entry_points.txt
ayx_blackbird-1.0.0a2.dist-info/top_level.txt
ayx_blackbird-1.0.0a2.dist-info/RECORD
